[
  {
    "spellID": "hatchet_dmgpernearbyenemy_detection",
    "statusEffects": "",
    "statusEffectDurations": "",
    "revive": "",
    "siphon": "",
    "attachToOwner": true,
    "stickWhenAttached": "",
    "storeOffsetWhenStuckToGDE": "",
    "spawnSecondaryOnElapsed": "",
    "spawnSecondaryOnCollision": false,
    "endOnCasterDeath": "",
    "ignoreTargetIfAtDeathsDoor": "",
    "ignoreTargetIfDead": "",
    "useCameraTargetLock": "",
    "trackNumInVolume": true,
    "clearOnExit": true,
    "clearOnEnd": true,
    "manaCost": "",
    "useStatusEffectDuration": false,
    "duration": -1,
    "durationScaling": "",
    "height": null,
    "length": "",
    "radius": 5,
    "innerRadius": "",
    "radiusScaling": "",
    "maxRadiusScaling": "",
    "castDistance": 0,
    "castHeight": 5,
    "castRadius": 5,
    "coneAngle": "",
    "coneWidth": "",
    "channelTime": 0,
    "chainDelayDuration": "",
    "maxChainNum": "",
    "useChainCasterPaperdoll": "",
    "numToSpawn": "",
    "numToSpawnBeforeFail": "",
    "spawnRate": "",
    "spawnAngle": "",
    "secondarySpellProjectileLaunchAngles": "",
    "scaleWithCharacterBoundingBox": "",
    "scaleWithDynamicScale": "",
    "targetTypes": "Enemy",
    "spellTypes": "Ability",
    "castingTypes": "AoE",
    "hitAiTarget": "",
    "overrideTargetForAiThreat": "",
    "shapeTypes": "Sphere",
    "damageType": "",
    "checkObstructions": true,
    "ignoreOverheadCollision": true,
    "ignoreStructures": "",
    "ignoreSelf": "",
    "rangedAttackProfile": "",
    "rangedAttackName": "",
    "fireJointName": "",
    "projPosOffsetX": "",
    "projPosOffsetY": "",
    "projPosOffsetZ": "",
    "projRotOffsetX": "",
    "projRotOffsetY": "",
    "projRotOffsetZ": "",
    "charRelPosOffsetX": "",
    "charRelPosOffsetY": "",
    "charRelPosOffsetZ": "",
    "charRelRotOffsetX": "",
    "charRelRotOffsetY": "",
    "charRelRotOffsetZ": "",
    "projRaycastOrientation": "",
    "damageTable": "",
    "damageTableRow": "",
    "abilityId": "Passive_Hatchet_Berserk_DMGPerNearbyEnemy",
    "targetAbilityCondition": "",
    "beamEffect": "",
    "indicatorVFX": "",
    "spellPrefabPath": "Items/Weapons/spell_NumAroundMe_Enemy",
    "secondaryPrefabPath": "",
    "secondarySpellID": "",
    "tertiaryPrefabPath": "",
    "tertiarySpellID": ""
  },
  {
    "spellID": "hatchet_spell_infectedthrowbase",
    "statusEffects": "",
    "statusEffectDurations": "",
    "revive": "",
    "siphon": "",
    "attachToOwner": false,
    "stickWhenAttached": "",
    "storeOffsetWhenStuckToGDE": "",
    "spawnSecondaryOnElapsed": "",
    "spawnSecondaryOnCollision": true,
    "endOnCasterDeath": "",
    "ignoreTargetIfAtDeathsDoor": "",
    "ignoreTargetIfDead": "",
    "useCameraTargetLock": "",
    "trackNumInVolume": false,
    "clearOnExit": true,
    "clearOnEnd": true,
    "manaCost": "",
    "useStatusEffectDuration": false,
    "duration": -1,
    "durationScaling": "",
    "height": 5,
    "length": "",
    "radius": 3,
    "innerRadius": "",
    "radiusScaling": "",
    "maxRadiusScaling": "",
    "castDistance": 30,
    "castHeight": null,
    "castRadius": null,
    "coneAngle": "",
    "coneWidth": "",
    "channelTime": 0,
    "chainDelayDuration": "",
    "maxChainNum": "",
    "useChainCasterPaperdoll": "",
    "numToSpawn": "",
    "numToSpawnBeforeFail": "",
    "spawnRate": "",
    "spawnAngle": "",
    "secondarySpellProjectileLaunchAngles": "",
    "scaleWithCharacterBoundingBox": "",
    "scaleWithDynamicScale": "",
    "targetTypes": "Enemy",
    "spellTypes": "Ability",
    "castingTypes": "Projectile",
    "hitAiTarget": "",
    "overrideTargetForAiThreat": "",
    "shapeTypes": "",
    "damageType": "Slash",
    "checkObstructions": true,
    "ignoreOverheadCollision": true,
    "ignoreStructures": "",
    "ignoreSelf": "",
    "rangedAttackProfile": "Hatchet",
    "rangedAttackName": "PowerThrow",
    "fireJointName": "right_hand_attach",
    "projPosOffsetX": "",
    "projPosOffsetY": "",
    "projPosOffsetZ": "",
    "projRotOffsetX": "",
    "projRotOffsetY": "",
    "projRotOffsetZ": "",
    "charRelPosOffsetX": "",
    "charRelPosOffsetY": "",
    "charRelPosOffsetZ": "",
    "charRelRotOffsetX": "",
    "charRelRotOffsetY": "",
    "charRelRotOffsetZ": "",
    "projRaycastOrientation": "",
    "damageTable": "DamageTable",
    "damageTableRow": "Hatchet_Damage_InfectedThrow",
    "abilityId": "Ability_Hatchet_InfectedThrow",
    "targetAbilityCondition": "",
    "beamEffect": "",
    "indicatorVFX": "",
    "spellPrefabPath": "Items/Weapons/basic_thrown",
    "secondaryPrefabPath": "",
    "secondarySpellID": "",
    "tertiaryPrefabPath": "",
    "tertiarySpellID": ""
  },
  {
    "spellID": "hatchet_spell_infectedthrowprojectile",
    "statusEffects": "",
    "statusEffectDurations": "",
    "revive": "",
    "siphon": "",
    "attachToOwner": false,
    "stickWhenAttached": "",
    "storeOffsetWhenStuckToGDE": "",
    "spawnSecondaryOnElapsed": "",
    "spawnSecondaryOnCollision": true,
    "endOnCasterDeath": "",
    "ignoreTargetIfAtDeathsDoor": "",
    "ignoreTargetIfDead": "",
    "useCameraTargetLock": "",
    "trackNumInVolume": false,
    "clearOnExit": true,
    "clearOnEnd": true,
    "manaCost": "",
    "useStatusEffectDuration": false,
    "duration": -1,
    "durationScaling": "",
    "height": 5,
    "length": "",
    "radius": 3,
    "innerRadius": "",
    "radiusScaling": "",
    "maxRadiusScaling": "",
    "castDistance": 30,
    "castHeight": null,
    "castRadius": null,
    "coneAngle": "",
    "coneWidth": "",
    "channelTime": 0,
    "chainDelayDuration": "",
    "maxChainNum": "",
    "useChainCasterPaperdoll": "",
    "numToSpawn": "",
    "numToSpawnBeforeFail": "",
    "spawnRate": "",
    "spawnAngle": "",
    "secondarySpellProjectileLaunchAngles": "",
    "scaleWithCharacterBoundingBox": "",
    "scaleWithDynamicScale": "",
    "targetTypes": "Enemy",
    "spellTypes": "Ability",
    "castingTypes": "Projectile",
    "hitAiTarget": "",
    "overrideTargetForAiThreat": "",
    "shapeTypes": "",
    "damageType": "Slash",
    "checkObstructions": true,
    "ignoreOverheadCollision": true,
    "ignoreStructures": "",
    "ignoreSelf": "",
    "rangedAttackProfile": "Hatchet",
    "rangedAttackName": "PowerThrow",
    "fireJointName": "right_hand_attach",
    "projPosOffsetX": "",
    "projPosOffsetY": "",
    "projPosOffsetZ": "",
    "projRotOffsetX": "",
    "projRotOffsetY": "",
    "projRotOffsetZ": "",
    "charRelPosOffsetX": "",
    "charRelPosOffsetY": "",
    "charRelPosOffsetZ": "",
    "charRelRotOffsetX": "",
    "charRelRotOffsetY": "",
    "charRelRotOffsetZ": "",
    "projRaycastOrientation": "",
    "damageTable": "DamageTable",
    "damageTableRow": "Hatchet_Damage_InfectedThrow",
    "abilityId": "Ability_Hatchet_InfectedThrow",
    "targetAbilityCondition": "",
    "beamEffect": "",
    "indicatorVFX": "",
    "spellPrefabPath": "Items/Weapons/basic_thrown",
    "secondaryPrefabPath": "Items/Weapons/Spell_Hatchet_Infected_Cloud",
    "secondarySpellID": "hatchet_spell_infectedthrowaoe",
    "tertiaryPrefabPath": "",
    "tertiarySpellID": ""
  },
  {
    "spellID": "hatchet_spell_infectedthrowaoe",
    "statusEffects": "Hatchet_Infected_DiseaseWeakBuff",
    "statusEffectDurations": "",
    "revive": "",
    "siphon": "",
    "attachToOwner": false,
    "stickWhenAttached": "",
    "storeOffsetWhenStuckToGDE": "",
    "spawnSecondaryOnElapsed": "",
    "spawnSecondaryOnCollision": false,
    "endOnCasterDeath": "",
    "ignoreTargetIfAtDeathsDoor": "",
    "ignoreTargetIfDead": "",
    "useCameraTargetLock": "",
    "trackNumInVolume": false,
    "clearOnExit": true,
    "clearOnEnd": false,
    "manaCost": "",
    "useStatusEffectDuration": true,
    "duration": 5000,
    "durationScaling": "",
    "height": 5,
    "length": "",
    "radius": 3,
    "innerRadius": "",
    "radiusScaling": "",
    "maxRadiusScaling": "",
    "castDistance": 25,
    "castHeight": 5,
    "castRadius": 5,
    "coneAngle": "",
    "coneWidth": "",
    "channelTime": 0,
    "chainDelayDuration": "",
    "maxChainNum": "",
    "useChainCasterPaperdoll": "",
    "numToSpawn": "",
    "numToSpawnBeforeFail": "",
    "spawnRate": "",
    "spawnAngle": "",
    "secondarySpellProjectileLaunchAngles": "",
    "scaleWithCharacterBoundingBox": "",
    "scaleWithDynamicScale": "",
    "targetTypes": "Enemy",
    "spellTypes": "Ability",
    "castingTypes": "AoE",
    "hitAiTarget": "",
    "overrideTargetForAiThreat": "",
    "shapeTypes": "Sphere",
    "damageType": "Slash",
    "checkObstructions": true,
    "ignoreOverheadCollision": true,
    "ignoreStructures": "",
    "ignoreSelf": "",
    "rangedAttackProfile": "",
    "rangedAttackName": "",
    "fireJointName": "",
    "projPosOffsetX": "",
    "projPosOffsetY": "",
    "projPosOffsetZ": "",
    "projRotOffsetX": "",
    "projRotOffsetY": "",
    "projRotOffsetZ": "",
    "charRelPosOffsetX": "",
    "charRelPosOffsetY": "",
    "charRelPosOffsetZ": "",
    "charRelRotOffsetX": "",
    "charRelRotOffsetY": "",
    "charRelRotOffsetZ": "",
    "projRaycastOrientation": "",
    "damageTable": "",
    "damageTableRow": "",
    "abilityId": "",
    "targetAbilityCondition": "",
    "beamEffect": "",
    "indicatorVFX": "",
    "spellPrefabPath": "Items/Weapons/Spell_Hatchet_Infected_Cloud",
    "secondaryPrefabPath": "",
    "secondarySpellID": "",
    "tertiaryPrefabPath": "",
    "tertiarySpellID": ""
  },
  {
    "spellID": "hatchet_spell_aimedthrow",
    "statusEffects": "",
    "statusEffectDurations": "",
    "revive": "",
    "siphon": "",
    "attachToOwner": false,
    "stickWhenAttached": "",
    "storeOffsetWhenStuckToGDE": "",
    "spawnSecondaryOnElapsed": "",
    "spawnSecondaryOnCollision": true,
    "endOnCasterDeath": "",
    "ignoreTargetIfAtDeathsDoor": "",
    "ignoreTargetIfDead": "",
    "useCameraTargetLock": "",
    "trackNumInVolume": false,
    "clearOnExit": true,
    "clearOnEnd": true,
    "manaCost": "",
    "useStatusEffectDuration": false,
    "duration": -1,
    "durationScaling": "",
    "height": 5,
    "length": "",
    "radius": 3,
    "innerRadius": "",
    "radiusScaling": "",
    "maxRadiusScaling": "",
    "castDistance": 30,
    "castHeight": null,
    "castRadius": null,
    "coneAngle": "",
    "coneWidth": "",
    "channelTime": 0,
    "chainDelayDuration": "",
    "maxChainNum": "",
    "useChainCasterPaperdoll": "",
    "numToSpawn": "",
    "numToSpawnBeforeFail": "",
    "spawnRate": "",
    "spawnAngle": "",
    "secondarySpellProjectileLaunchAngles": "",
    "scaleWithCharacterBoundingBox": "",
    "scaleWithDynamicScale": "",
    "targetTypes": "Enemy",
    "spellTypes": "Ability",
    "castingTypes": "Projectile",
    "hitAiTarget": "",
    "overrideTargetForAiThreat": "",
    "shapeTypes": "",
    "damageType": "Slash",
    "checkObstructions": true,
    "ignoreOverheadCollision": true,
    "ignoreStructures": "",
    "ignoreSelf": "",
    "rangedAttackProfile": "Hatchet",
    "rangedAttackName": "Basic",
    "fireJointName": "right_hand_attach",
    "projPosOffsetX": "",
    "projPosOffsetY": "",
    "projPosOffsetZ": "",
    "projRotOffsetX": "",
    "projRotOffsetY": "",
    "projRotOffsetZ": "",
    "charRelPosOffsetX": "",
    "charRelPosOffsetY": "",
    "charRelPosOffsetZ": "",
    "charRelRotOffsetX": "",
    "charRelRotOffsetY": "",
    "charRelRotOffsetZ": "",
    "projRaycastOrientation": "",
    "damageTable": "DamageTable",
    "damageTableRow": "Hatchet_Damage_AimedThrow",
    "abilityId": "Passive_Hatchet_ThrowingAxe_AimedThrow",
    "targetAbilityCondition": "",
    "beamEffect": "",
    "indicatorVFX": "",
    "spellPrefabPath": "Items/Weapons/basic_thrown",
    "secondaryPrefabPath": "",
    "secondarySpellID": "",
    "tertiaryPrefabPath": "",
    "tertiarySpellID": ""
  }
]